identt/__init__.py
identt/client.py
identt/iden.py
identt-0.1.20.dist-info/METADATA
identt-0.1.20.dist-info/WHEEL
identt-0.1.20.dist-info/top_level.txt
identt-0.1.20.dist-info/RECORD
