Metadata-Version: 2.1
Name: identt
Version: 0.1.20
Summary: Python SDK for Iden API interactions
Author: brdge.ai
Requires-Dist: requests
